Workbook

Sheet 総合評価
A1: ① 総合評価 — 6観点の加重スコアで楔を検証（篠塚流「市場選定が9割」）
A2: ①市場は『市場規模試算』シートから自動連携。②〜⑥は判断値（1〜5, 黄色セルで調整可）。重みも黄色セルで可変。
A4: 重み（合計1.00） | B4: シナリオA：市場最優先 | C4: シナリオB：ブランド適合重視
A5: ①市場規模 | B5: 0.35 | C5: 0.2
A6: ②VPの立てやすさ | B6: 0.15 | C6: 0.25
A7: ③CAN適合 | B7: 0.15 | C7: 0.2
A8: ④緊急度/WTP | B8: 0.2 | C8: 0.1
A9: ⑤供給確保 | B9: 0.1 | C9: 0.1
A10: ⑥制約両立 | B10: 0.05 | C10: 0.15
A11: 合計 | B11: =SUM(B5:B10) | C11: =SUM(C5:C10)
A14: 楔（悩み × 形態） | B14: ①市場 | C14: ②VP | D14: ③CAN | E14: ④緊急 | F14: ⑤供給 | G14: ⑥制約 | H14: A総合 | I14: A順位 | J14: B総合 | K14: B順位 | L14: 判定
A15: 薄毛 × 医療連携（AGA） | B15: =市場規模試算!G5 | C15: 2 | D15: 3.5 | E15: 5 | F15: 2.5 | G15: 2 | H15: =B15*$B$5+C15*$B$6+D15*$B$7+E15*$B$8+F15*$B$9+G15*$B$10 | I15: =RANK(H15,$H$15:$H$21) | J15: =B15*$C$5+C15*$C$6+D15*$C$7+E15*$C$8+F15*$C$9+G15*$C$10 | K15: =RANK(J15,$J$15:$J$21) | L15: 市場・緊急度は最強。だが競合飽和/供給難/紹介料規制で②⑤⑥が弱い＝HRの魂と衝突。
A16: 第一印象 × 一日パッケージ（メイク・服・写真） | B16: =市場規模試算!G6 | C16: 5 | D16: 5 | E16: 4 | F16: 2 | G16: 5 | H16: =B16*$B$5+C16*$B$6+D16*$B$7+E16*$B$8+F16*$B$9+G16*$B$10 | I16: =RANK(H16,$H$15:$H$21) | J16: =B16*$C$5+C16*$C$6+D16*$C$7+E16*$C$8+F16*$C$9+G16*$C$10 | K16: =RANK(J16,$J$15:$J$21) | L16: VP・CAN・制約適合が最強＝HRの中立コンシェルジュど真ん中。弱点は市場規模と供給(メイク人材)。
A17: 肌 × 美容皮膚科連携 | B17: =市場規模試算!G7 | C17: 2.5 | D17: 3.5 | E17: 3 | F17: 2.5 | G17: 2 | H17: =B17*$B$5+C17*$B$6+D17*$B$7+E17*$B$8+F17*$B$9+G17*$B$10 | I17: =RANK(H17,$H$15:$H$21) | J17: =B17*$C$5+C17*$C$6+D17*$C$7+E17*$C$8+F17*$C$9+G17*$C$10 | K17: =RANK(J17,$J$15:$J$21) | L17: 中庸。医療広告飽和で差別化しづらい。
A18: 体型 × トレーニング/栄養 | B18: =市場規模試算!G8 | C18: 2.5 | D18: 3.5 | E18: 3.5 | F18: 4 | G18: 4 | H18: =B18*$B$5+C18*$B$6+D18*$B$7+E18*$B$8+F18*$B$9+G18*$B$10 | I18: =RANK(H18,$H$15:$H$21) | J18: =B18*$C$5+C18*$C$6+D18*$C$7+E18*$C$8+F18*$C$9+G18*$C$10 | K18: =RANK(J18,$J$15:$J$21) | L18: 供給が容易・制約と両立◎でバランス良。緊急度は中。
A19: ヒゲ・体毛 × 脱毛 | B19: =市場規模試算!G9 | C19: 2 | D19: 3 | E19: 3 | F19: 3.5 | G19: 3 | H19: =B19*$B$5+C19*$B$6+D19*$B$7+E19*$B$8+F19*$B$9+G19*$B$10 | I19: =RANK(H19,$H$15:$H$21) | J19: =B19*$C$5+C19*$C$6+D19*$C$7+E19*$C$8+F19*$C$9+G19*$C$10 | K19: =RANK(J19,$J$15:$J$21) | L19: 市場中規模だが広告飽和。差別化余地小。
A20: 内側 × 血液最適化 | B20: =市場規模試算!G10 | C20: 4 | D20: 2.5 | E20: 2 | F20: 2 | G20: 2.5 | H20: =B20*$B$5+C20*$B$6+D20*$B$7+E20*$B$8+F20*$B$9+G20*$B$10 | I20: =RANK(H20,$H$15:$H$21) | J20: =B20*$C$5+C20*$C$6+D20*$C$7+E20*$C$8+F20*$C$9+G20*$C$10 | K20: =RANK(J20,$J$15:$J$21) | L20: 需要未顕在で市場小。HRの独自性は高いが今は早い。
A21: 心 × カウンセリング | B21: =市場規模試算!G11 | C21: 3 | D21: 2.5 | E21: 3 | F21: 3.5 | G21: 3.5 | H21: =B21*$B$5+C21*$B$6+D21*$B$7+E21*$B$8+F21*$B$9+G21*$B$10 | I21: =RANK(H21,$H$15:$H$21) | J21: =B21*$C$5+C21*$C$6+D21*$C$7+E21*$C$8+F21*$C$9+G21*$C$10 | K21: =RANK(J21,$J$15:$J$21) | L21: 市場小・相談化しにくい。将来のモジュール向き。
A23: 読み方
A24: ・シナリオA（市場最優先＝篠塚の『市場が9割』）では 薄毛 が突出。市場規模と緊急度が支配的だから。
A25: ・シナリオB（中立コンシェルジュというブランドの魂を重視）では 第一印象 が逆転首位。②VP・③CAN・⑥制約でHRのど真ん中だから。
A26: ・つまり『どちらが正しい市場か』は、HRが何に張る会社かで決まる。数字は判断を代替せず、争点を可視化する。
A27: ・現実解：ブランド適合の高い【第一印象】を『最初の楔』に据えて1回届け切り、市場の大きい【薄毛】へ中立連携で橋渡しする『順番』（＝戦略）。
A28: ・次に埋めるべき空欄＝①市場スコアの根拠（GA/Search Consoleの記事別PV・流入クエリ・相談転換）。ここが入ると①が実測に変わる。

Sheet 市場規模試算
A1: ② 市場規模試算（TAM / SAM）— HRが束ねられる年間売上プールを試算
A2: 黄色セル＝可変の前提（実データで上書き可）／白セル＝自動計算。対象男性人口ベース＝20〜49歳 約2,000万人。
A4: 楔（悩み × 形態） | B4: 対象率 (%) | C4: 対象顧客 (万人) | D4: HR単価 (円) | E4: 年間 頻度 | F4: HR-SAM (億円) | G4: ①市場スコア (SAM相対5点) | H4: 参考:カテゴリ 市場(億円) | I4: 出典・前提
A5: 薄毛 × 医療連携（AGA） | B5: 5 | C5: =2000*B5/100 | D5: 50000 | E5: 1.2 | F5: =C5*D5*E5/10000 | G5: =F5/MAX($F$5:$F$11)*5 | H5: 2459 | I5: 薄毛の自覚層対策市場 約2,459億円（薄毛対策・予防 計5,137億の一部, 2025推計）
A6: 第一印象 × 一日パッケージ（メイク・服・写真） | B6: 2 | C6: =2000*B6/100 | D6: 80000 | E6: 0.5 | F6: =C6*D6*E6/10000 | G6: =F6/MAX($F$5:$F$11)*5 | H6: 80 | I6: 該当カテゴリは未成立。メンズメイク497億の一部+スタイリング+撮影を新規に束ねる想定（HRが創出）
A7: 肌 × 美容皮膚科連携 | B7: 3 | C7: =2000*B7/100 | D7: 40000 | E7: 1.5 | F7: =C7*D7*E7/10000 | G7: =F7/MAX($F$5:$F$11)*5 | H7: 900 | I7: 美容医療総市場6,310億円(2024)の男性・肌分を約15%と仮置き。メンズ基礎化粧品438億は別枠
A8: 体型 × トレーニング/栄養 | B8: 3 | C8: =2000*B8/100 | D8: 60000 | E8: 1 | F8: =C8*D8*E8/10000 | G8: =F8/MAX($F$5:$F$11)*5 | H8: 200 | I8: パーソナルジム市場300億円超の男性分（約6〜7割）を仮置き。フィットネス全体は7,100億
A9: ヒゲ・体毛 × 脱毛 | B9: 4 | C9: =2000*B9/100 | D9: 30000 | E9: 0.8 | F9: =C9*D9*E9/10000 | G9: =F9/MAX($F$5:$F$11)*5 | H9: 635 | I9: 男性脱毛市場 635億円（2024, 4年で1.8倍）
A10: 内側 × 血液最適化 | B10: 1 | C10: =2000*B10/100 | D10: 30000 | E10: 1 | F10: =C10*D10*E10/10000 | G10: =F10/MAX($F$5:$F$11)*5 | H10: 100 | I10: 予防・検査領域は未成立。新規創出前提の仮置き
A11: 心 × カウンセリング | B11: 2 | C11: =2000*B11/100 | D11: 20000 | E11: 2 | F11: =C11*D11*E11/10000 | G11: =F11/MAX($F$5:$F$11)*5 | H11: 80 | I11: メンズ向けカウンセリングは市場未顕在。仮置き
A13: SAM = 対象顧客(万人) × HR単価(円) × 年間頻度 ÷ 10,000。HRが全需要を束ねた場合の年間売上プール（上限）。実際の獲得はこの数%。

Sheet 判断根拠
A1: ③ 判断根拠 — ②〜⑥スコア（1=低い/悪い 〜 5=高い/良い）の理由
A3: 楔 | B3: ②VPの立てやすさ（競合の薄さ） | C3: ③CAN適合（メディア/コーディネート力） | D3: ④緊急度/WTP（今すぐ払うか） | E3: ⑤供給確保（1人/1院を押さえられるか） | F3: ⑥制約両立（中立・紹介料0）
A4: 薄毛×医療 | B4: 医療広告が飽和＝篠塚が避けた『ホテル予約』側。差別化の隙間が狭い | C4: 記事資産は効くが施術は自社不可・紹介のみ＝コーディネート余地は中 | D4: 深刻・緊急・高単価継続。WTP最強 | E4: 自由診療クリニックの提携が必要で難度高 | F4: 患者紹介料は規制強く法務リスク大＝中立/紹介料0と衝突
A5: 第一印象×一日 | B5: コンシェルジュ型競合がほぼ不在＝ブルーオーシャン。HR独自VPが立つ | C5: メディアの強みと直結・『束ねる』能力ど真ん中＝最適合 | D5: 転機（婚活/昇進/写真）で高いが単発になりがち | E5: メンズメイク対応人材が希少＝HR自身が最難関と認識 | F5: 自社パッケージの原価マージン＝キックバックでなく健全に両立◎
A6: 肌×美容皮膚科 | B6: 美容皮膚科の広告多く差別化しづらい | C6: 記事は効く。施術は紹介 | D6: 肌悩みは中程度の緊急度 | E6: クリニック提携が必要 | F6: 医療＝紹介料規制と衝突
A7: 体型×トレ/栄養 | B7: パーソナルジム飽和気味だが『中立で選ぶ』余地はある | C7: 記事＋コーディネート効く | D7: 中〜高。可視化しやすくWTPは出る | E7: トレーナー/栄養士は多数＝確保容易 | F7: 下請けマージンで両立可
A8: ヒゲ体毛×脱毛 | B8: 広告飽和で差別化余地小 | C8: 記事は効く | D8: 中程度 | E8: クリニック/サロン多数＝確保容易 | F8: 医療脱毛は規制、サロンはグレー
A9: 内側×血液 | B9: 競合ほぼ不在だが需要が未顕在 | C9: 専門性高くCANとの距離が遠い | D9: 顕在化が弱く緊急度低 | E9: 検査ラボ＋医師が必要で難 | F9: 医療周辺で要法務確認
A10: 心×カウンセリング | B10: 競合少ないが相談として顕在化しにくい | C10: コーディネートが効きにくい | D10: 痛みは深いが相談化しづらい | E10: カウンセラー確保は比較的容易 | F10: 非医療で両立しやすい

Sheet 前提・出典
A1: ④ 前提・出典・凡例
A3: 凡例
A4: 黄色セル＝入力（前提/判断値）。青字。実データで上書きする。
A5: 白/緑セル＝自動計算（数式）。触らない。
A7: 主要前提 | B7: 値 | C7: 根拠/出典
A8: 対象男性人口（20〜49歳） | B8: 約2,000万人 | C8: 総務省人口推計ベースの概算（20代約590万+30代約650万+40代約800万）
A9: 対象率（悩み保有×本気の支払層） | B9: 楔ごとに1〜5% | C9: HR仮置き。実データ（記事PV・相談転換）で要更新
A10: HR単価・年間頻度 | B10: 楔ごと | C10: HRのコーディネート込み想定単価。要検証（Concierge MVPで実測）
A12: 市場規模データ（出典）
A13: 薄毛対策・予防市場 | B13: 約5,137億円（うち自覚層対策2,459億, 2025推計） | C13: news-postseven / 矢野経済系
A14: 美容医療総市場 | B14: 6,310億円（2024, 前年比+6.2%） | C14: 各種業界調査
A15: 男性脱毛市場 | B15: 635億円（2024, 4年で1.8倍） | C15: リクルート ホットペッパービューティーアカデミー
A16: 男性化粧品市場 | B16: 497億円（2024, インテージ）／基礎化粧品438億 | C16: インテージ / 富士経済
A17: メンズ整肌料（スキンケア） | B17: 314億円（2024, +6.4%） | C17: 富士経済
A18: フィットネス市場 | B18: 約7,100億円（2024, パーソナルジム300億超） | C18: 帝国データバンク / 矢野経済
A20: 注意
A21: SAMは『HRが全需要を束ねた場合』の上限。実獲得は数%。カテゴリ市場は参考値で、HRのSAMとは定義が異なる。
A22: 市場規模の絶対額より、①〜⑥の相対比較と『順番の設計』に使うのが本シートの目的。
